vader_sentiment_tool/__init__.py
vader_sentiment_tool/analyzer.py
vader_sentiment_tool-0.1.0.dist-info/METADATA
vader_sentiment_tool-0.1.0.dist-info/WHEEL
vader_sentiment_tool-0.1.0.dist-info/top_level.txt
vader_sentiment_tool-0.1.0.dist-info/RECORD
