Metadata-Version: 2.4
Name: vader-sentiment-tool
Version: 0.1.0
Summary: A simple sentiment analyzer using VADER
Author: Your Name
Author-email: your.email@example.com
Requires-Python: >=3.7
Requires-Dist: vaderSentiment
Dynamic: author
Dynamic: author-email
Dynamic: requires-dist
Dynamic: requires-python
Dynamic: summary
